aifeynman/10ops.txt
aifeynman/14ops.txt
aifeynman/19ops.txt
aifeynman/7ops.txt
aifeynman/RPN_to_eq.py
aifeynman/RPN_to_pytorch.py
aifeynman/S_NN_eval.py
aifeynman/S_NN_get_gradients.py
aifeynman/S_NN_train.py
aifeynman/S_add_bf_on_numbers_on_pareto.py
aifeynman/S_add_snap_expr_on_pareto.py
aifeynman/S_add_sym_on_pareto.py
aifeynman/S_brute_force.py
aifeynman/S_brute_force_comp.py
aifeynman/S_brute_force_gen_sym.py
aifeynman/S_brute_force_number.py
aifeynman/S_change_output.py
aifeynman/S_combine_pareto.py
aifeynman/S_compositionality.py
aifeynman/S_final_gd.py
aifeynman/S_gen_sym.py
aifeynman/S_get_expr_complexity.py
aifeynman/S_get_number_DL.py
aifeynman/S_get_number_DL_snapped.py
aifeynman/S_get_symbolic_expr_error.py
aifeynman/S_gradient_decomposition.py
aifeynman/S_polyfit.py
aifeynman/S_polyfit_utils.py
aifeynman/S_remove_input_neuron.py
aifeynman/S_run_aifeynman.py
aifeynman/S_run_bf_polyfit.py
aifeynman/S_separability.py
aifeynman/S_snap.py
aifeynman/S_symmetry.py
aifeynman/__init__.py
aifeynman/_symbolic_regress1.cpython-37m-darwin.so
aifeynman/_symbolic_regress2.cpython-37m-darwin.so
aifeynman/_symbolic_regress3.cpython-37m-darwin.so
aifeynman/_symbolic_regress_mdl2.cpython-37m-darwin.so
aifeynman/_symbolic_regress_mdl3.cpython-37m-darwin.so
aifeynman/_symbolic_regress_mdl4.cpython-37m-darwin.so
aifeynman/_symbolic_regress_mdl5.cpython-37m-darwin.so
aifeynman/arity2templates.txt
aifeynman/dimensionalAnalysis.py
aifeynman/getPowers.py
aifeynman/get_demos.py
aifeynman/get_pareto.py
aifeynman/resources.py
aifeynman/symbolic_regress1.f90
aifeynman/symbolic_regress2.f90
aifeynman/symbolic_regress3.f90
aifeynman/symbolic_regress_mdl2.f90
aifeynman/symbolic_regress_mdl3.f90
aifeynman/symbolic_regress_mdl4.f90
aifeynman/symbolic_regress_mdl5.f90
aifeynman/test_points.py
aifeynman/tools.f90
aifeynman/_symbolic_regress1.cpython-37m-darwin.so.dSYM/Contents/Info.plist
aifeynman-2.0.7.dist-info/LICENSE
aifeynman-2.0.7.dist-info/METADATA
aifeynman-2.0.7.dist-info/WHEEL
aifeynman-2.0.7.dist-info/entry_points.txt
aifeynman-2.0.7.dist-info/top_level.txt
aifeynman-2.0.7.dist-info/RECORD
